octodns_cloudns/__init__.py
octodns_cloudns-0.0.9.dist-info/LICENSE
octodns_cloudns-0.0.9.dist-info/METADATA
octodns_cloudns-0.0.9.dist-info/WHEEL
octodns_cloudns-0.0.9.dist-info/top_level.txt
octodns_cloudns-0.0.9.dist-info/RECORD
