Metadata-Version: 2.1
Name: octodns-cloudns
Version: 0.0.9
Summary: ClouDNS API provider for octoDNS
Home-page: https://github.com/octodns/octodns-cloudns
Author: ClouDNS
Author-email: support@cloudns.net
License: MIT
Requires-Python: >=3.6
License-File: LICENSE
Requires-Dist: octodns >=0.9.17
Requires-Dist: requests >=2.27.0
Provides-Extra: dev
Requires-Dist: pytest ; extra == 'dev'
Requires-Dist: pytest-cov ; extra == 'dev'
Requires-Dist: pytest-network ; extra == 'dev'
Requires-Dist: requests-mock ; extra == 'dev'
Requires-Dist: black <24.0.0,>=23.1.0 ; extra == 'dev'
Requires-Dist: build >=0.7.0 ; extra == 'dev'
Requires-Dist: isort >=5.11.5 ; extra == 'dev'
Requires-Dist: pyflakes >=2.2.0 ; extra == 'dev'
Requires-Dist: readme-renderer[md] >=26.0 ; extra == 'dev'
Requires-Dist: twine >=3.4.2 ; extra == 'dev'
Provides-Extra: test
Requires-Dist: pytest ; extra == 'test'
Requires-Dist: pytest-cov ; extra == 'test'
Requires-Dist: pytest-network ; extra == 'test'
Requires-Dist: requests-mock ; extra == 'test'
